chrispile/__init__.py
chrispile/__main__.py
chrispile/api.py
chrispile/config.py
chrispile/render.py
chrispile/run.py
chrispile/store.py
chrispile/util.py
chrispile/templates/exec.sh
chrispile/templates/mounts.sh
chrispile/templates/rootless_docker.sh
chrispile-1.2.4.dist-info/LICENSE
chrispile-1.2.4.dist-info/METADATA
chrispile-1.2.4.dist-info/WHEEL
chrispile-1.2.4.dist-info/entry_points.txt
chrispile-1.2.4.dist-info/top_level.txt
chrispile-1.2.4.dist-info/RECORD
