Metadata-Version: 2.1
Name: chrispile
Version: 1.2.4
Summary: Syntactic sugar for running ChRIS apps locally
Home-page: https://github.com/FNNDSC/chrispile
Author: Jennings Zhang
Author-email: Jennings.Zhang@childrens.harvard.edu
License: MIT
Platform: UNKNOWN
Classifier: Programming Language :: Python :: 3 :: Only
Classifier: Programming Language :: Python :: 3.8
Classifier: Programming Language :: Python :: 3.9
Classifier: License :: OSI Approved :: MIT License
Classifier: Operating System :: POSIX :: Linux
Classifier: Topic :: Scientific/Engineering :: Medical Science Apps.
Classifier: Topic :: Software Development
Classifier: Topic :: System :: Software Distribution
Requires-Python: >=3.8
Requires-Dist: pyyaml
Requires-Dist: jinja2
